netgrab.py
setup.py
netgrab.egg-info/PKG-INFO
netgrab.egg-info/SOURCES.txt
netgrab.egg-info/dependency_links.txt
netgrab.egg-info/not-zip-safe
netgrab.egg-info/requires.txt
netgrab.egg-info/top_level.txt