Metadata-Version: 1.0
Name: netgrab
Version: 1.0
Summary: Add simplicity to getting basic dns information
Home-page: https://github.com/z4y/netgrab
Author: Cameron Poe
Author-email: cameron@zay.li
License: GNU
Platform: any
